assistant/__init__.py
assistant/prdocs.py
assistant/test_prdocs.py
config_builder/__init__.py
config_builder/clean_generated.py
config_builder/combined_generator.py
config_builder/json_schema_validator.py
config_builder/loaders.py
config_builder/materialize_all.py
config_builder/materializer.py
config_builder/test_combined_generator.py
config_builder/test_json_schema_validator.py
config_builder/test_materializer.py
config_builder/merger/__init__.py
config_builder/merger/libsonnet.py
config_builder/merger/test_libsonnet.py
config_builder/merger/test_yaml.py
config_builder/merger/yamljson.py
libsentrykube/__init__.py
libsentrykube/cluster.py
libsentrykube/config.py
libsentrykube/context.py
libsentrykube/customer.py
libsentrykube/datadog.py
libsentrykube/events.py
libsentrykube/ext.py
libsentrykube/gcloud.py
libsentrykube/git.py
libsentrykube/helm.py
libsentrykube/iap.py
libsentrykube/jira.py
libsentrykube/kube.py
libsentrykube/linear.py
libsentrykube/lint.py
libsentrykube/loader.py
libsentrykube/py.typed
libsentrykube/quickpatch.py
libsentrykube/reversemap.py
libsentrykube/service.py
libsentrykube/setup.py
libsentrykube/ssh.py
libsentrykube/utils.py
libsentrykube/kubectl/__init__.py
libsentrykube/kubectl/important_diffs.py
libsentrykube/tests/__init__.py
libsentrykube/tests/conftest.py
libsentrykube/tests/test_cluster.py
libsentrykube/tests/test_config.py
libsentrykube/tests/test_context.py
libsentrykube/tests/test_customer.py
libsentrykube/tests/test_datadog.py
libsentrykube/tests/test_deep_merge.py
libsentrykube/tests/test_ext.py
libsentrykube/tests/test_gcloud.py
libsentrykube/tests/test_git.py
libsentrykube/tests/test_iap.py
libsentrykube/tests/test_jira.py
libsentrykube/tests/test_kube.py
libsentrykube/tests/test_lint.py
libsentrykube/tests/test_quickpatch.py
libsentrykube/tests/test_reversemap.py
libsentrykube/tests/test_service.py
libsentrykube/tests/test_utils.py
pr_approver/__init__.py
pr_approver/approver.py
pr_approver/gh.py
pr_approver/rules.py
sentry_infra_tools-1.25.0.dist-info/METADATA
sentry_infra_tools-1.25.0.dist-info/WHEEL
sentry_infra_tools-1.25.0.dist-info/entry_points.txt
sentry_infra_tools-1.25.0.dist-info/top_level.txt
sentry_infra_tools-1.25.0.dist-info/RECORD
