Metadata-Version: 2.4
Name: sentry-infra-tools
Version: 1.25.0
Summary: Infrastructure tools used at Sentry
Author: Sentry
Author-email: oss@sentry.io
License: FSL-1.0-Apache-2.0
Requires-Python: >=3.11
Requires-Dist: click>=8.1.7
Requires-Dist: dictdiffer>=0.9.0
Requires-Dist: gitpython>=3.1.41
Requires-Dist: google_api_python_client>=2.137.0
Requires-Dist: google-cloud-secret-manager>=2.20.2
Requires-Dist: httpx>=0.27.2
Requires-Dist: Jinja2>=3.1.4
Requires-Dist: jsonpatch>=1.33
Requires-Dist: jsonpath_ng>=1.6.1
Requires-Dist: jsonschema>=4.23.0
Requires-Dist: kubernetes>=30.1.0
Requires-Dist: paramiko>=3.4.0
Requires-Dist: protobuf>=5.28.1
Requires-Dist: PyYAML>=6.0.1
Requires-Dist: referencing>=0.35.1
Requires-Dist: Requests>=2.32.3
Requires-Dist: sentry_jsonnet>=0.0.5
Requires-Dist: sentry_sdk>=2.10.0
Requires-Dist: setuptools>=69.0.3
Requires-Dist: tabulate>=0.9.0
Dynamic: author
Dynamic: author-email
Dynamic: license
Dynamic: requires-dist
Dynamic: requires-python
Dynamic: summary
